{
  "id": "aleph-alpha",
  "name": "Aleph Alpha",
  "aliases": [],
  "website": "aleph-alpha.com",
  "category": "foundation-model",
  "subcategory": "multimodal",
  "specialty": "Multimodal AI for enterprise.",
  "summary": "Aleph Alpha provides multimodal AI models, including large language and vision capabilities, for enterprise applications with a focus on sovereignty.",
  "segment": "global",
  "in_universe": true,
  "vc_attention_score": 85.9,
  "universe_rank": 19,
  "metrics": {
    "round_amount": {
      "metric": "round_amount",
      "value": 600000000.0,
      "unit": "USD",
      "range": {
        "low": 600000000.0,
        "high": 600000000.0
      },
      "as_of": "2026-04-26",
      "estimate_type": "consensus",
      "confidence": 0.675,
      "supporting_claims": [
        "clm_4c099ab1a8",
        "clm_b2c055d7af"
      ],
      "contradiction": false,
      "delta": {
        "previous": 600000000.0,
        "change_pct": 0.0,
        "since": "2026-04-26"
      },
      "history_ref": "history/aleph-alpha/round_amount.jsonl",
      "unconfirmed": false,
      "confirmed_value": null,
      "confirmed_as_of": null
    },
    "valuation": {
      "metric": "valuation",
      "value": 20000000000.0,
      "unit": "USD",
      "range": {
        "low": 20000000000.0,
        "high": 20000000000.0
      },
      "as_of": "2026-04-26",
      "estimate_type": "consensus",
      "confidence": 0.814,
      "supporting_claims": [
        "clm_d4e5d7bb02",
        "clm_a4ff17bb85",
        "clm_24f03f0946"
      ],
      "contradiction": false,
      "delta": {
        "previous": 20000000000.0,
        "change_pct": 0.0,
        "since": "2026-04-26"
      },
      "history_ref": "history/aleph-alpha/valuation.jsonl",
      "unconfirmed": false,
      "confirmed_value": null,
      "confirmed_as_of": null
    }
  },
  "last_updated": "2026-07-07"
}
