{
  "id": "databricks",
  "name": "Databricks",
  "aliases": [],
  "website": "databricks.com",
  "category": "ai-infra",
  "subcategory": "data-platform",
  "specialty": "AI data platform",
  "summary": "Databricks is a company that uses AI to create a data platform for businesses and organizations.",
  "segment": "global",
  "in_universe": true,
  "vc_attention_score": 92.8,
  "universe_rank": 4,
  "metrics": {
    "revenue_growth": {
      "metric": "revenue_growth",
      "value": 80.0,
      "unit": "pct",
      "range": null,
      "as_of": "2026-06-16",
      "estimate_type": "reported",
      "confidence": 0.264,
      "supporting_claims": [
        "clm_45db87797a"
      ],
      "contradiction": false,
      "delta": {
        "previous": 80.0,
        "change_pct": 0.0,
        "since": "2026-06-16"
      },
      "history_ref": "history/databricks/revenue_growth.jsonl",
      "unconfirmed": true,
      "confirmed_value": null,
      "confirmed_as_of": null
    },
    "valuation": {
      "metric": "valuation",
      "value": 134000000000.0,
      "unit": "USD",
      "range": null,
      "as_of": "2026-06-20",
      "estimate_type": "reported",
      "confidence": 0.501,
      "supporting_claims": [
        "clm_2a42b0d67e"
      ],
      "contradiction": false,
      "delta": {
        "previous": 134000000000.0,
        "change_pct": 0.0,
        "since": "2026-06-20"
      },
      "history_ref": "history/databricks/valuation.jsonl",
      "unconfirmed": false,
      "confirmed_value": null,
      "confirmed_as_of": null
    }
  },
  "last_updated": "2026-07-07"
}
