{
  "id": "neuralink",
  "name": "Neuralink",
  "aliases": [],
  "website": "neuralink.com",
  "category": "robotics",
  "subcategory": "humanoid",
  "specialty": "AI brain-machine interface",
  "summary": "Neuralink is a company that uses AI to develop brain-machine interfaces and robotic systems.",
  "segment": "global",
  "in_universe": false,
  "vc_attention_score": 0.0,
  "universe_rank": 142,
  "metrics": {
    "arr": {
      "metric": "arr",
      "value": 1000000000.0,
      "unit": "USD",
      "range": null,
      "as_of": "2025-07-23",
      "estimate_type": "reported",
      "confidence": 0.02,
      "supporting_claims": [
        "clm_12701c0e88"
      ],
      "contradiction": false,
      "delta": {
        "previous": 1000000000.0,
        "change_pct": 0.0,
        "since": "2025-07-23"
      },
      "history_ref": "history/neuralink/arr.jsonl",
      "unconfirmed": false,
      "confirmed_value": null,
      "confirmed_as_of": null
    }
  },
  "last_updated": "2026-07-07"
}
