{
  "id": "prosper-ai",
  "name": "Prosper AI",
  "aliases": [],
  "website": "prosper.ai",
  "category": "AI for healthcare operations",
  "segment": "global",
  "in_universe": false,
  "vc_attention_score": 62.4,
  "universe_rank": 110,
  "metrics": {
    "round_amount": {
      "metric": "round_amount",
      "value": 30000000.0,
      "unit": "USD",
      "range": {
        "low": 30000000.0,
        "high": 30000000.0
      },
      "as_of": "2026-06-24",
      "estimate_type": "consensus",
      "confidence": 0.97,
      "supporting_claims": [
        "clm_e9b11578f2",
        "clm_0aaa865587",
        "clm_e878983993",
        "clm_ad6bdeb869",
        "clm_2db7523f39"
      ],
      "contradiction": false,
      "delta": null,
      "history_ref": "history/prosper-ai/round_amount.jsonl"
    }
  },
  "last_updated": "2026-06-24"
}
